hydrofunctions/__init__.py
hydrofunctions/charts.py
hydrofunctions/exceptions.py
hydrofunctions/helpers.py
hydrofunctions/hydrofunctions.py
hydrofunctions/logging.py
hydrofunctions/station.py
hydrofunctions/usgs_rdb.py
hydrofunctions/validate.py
hydrofunctions/waterwatch.py
hydrofunctions-0.2.4.dist-info/LICENSE
hydrofunctions-0.2.4.dist-info/METADATA
hydrofunctions-0.2.4.dist-info/WHEEL
hydrofunctions-0.2.4.dist-info/top_level.txt
hydrofunctions-0.2.4.dist-info/RECORD
