Metadata-Version: 2.1
Name: hydrofunctions
Version: 0.2.4
Summary: A suite of convenience functions for exploring water data in a Jupyter Notebook
Home-page: https://github.com/mroberge/hydrofunctions
Author: Martin Roberge
Author-email: mroberge@towson.edu
License: MIT license
Project-URL: Documentation, https://hydrofunctions.readthedocs.io
Project-URL: Source, https://github.com/mroberge/hydrofunctions
Project-URL: Latest, https://github.com/mroberge/hydrofunctions/tree/develop
Project-URL: Issue Tracker, https://github.com/mroberge/hydrofunctions/issues
Keywords: hydrofunctions hydrology USGS stream gauge water NWIS
Classifier: Development Status :: 3 - Alpha
Classifier: Intended Audience :: Science/Research
Classifier: License :: OSI Approved :: MIT License
Classifier: Natural Language :: English
Classifier: Programming Language :: Python :: 3.8
Classifier: Programming Language :: Python :: 3.9
Classifier: Programming Language :: Python :: 3.10
Classifier: Programming Language :: Python :: 3.11
Classifier: Topic :: Scientific/Engineering :: Hydrology
Classifier: Topic :: Scientific/Engineering :: Information Analysis
Classifier: Topic :: Scientific/Engineering :: Visualization
Classifier: Topic :: Utilities
License-File: LICENSE
Requires-Dist: importlib-metadata
Requires-Dist: matplotlib
Requires-Dist: numpy (>=1.16.0)
Requires-Dist: pandas (>=2)
Requires-Dist: requests
Requires-Dist: IPython
Requires-Dist: pyarrow
Provides-Extra: dev
Requires-Dist: nbsphinx ; extra == 'dev'
Requires-Dist: pandoc ; extra == 'dev'
Requires-Dist: Sphinx (>=1.4.4) ; extra == 'dev'
Requires-Dist: black ; extra == 'dev'
Requires-Dist: build ; extra == 'dev'
Requires-Dist: bumpversion (>=0.5.3) ; extra == 'dev'
Requires-Dist: coverage (>=4.1) ; extra == 'dev'
Requires-Dist: cryptography (>=1.4) ; extra == 'dev'
Requires-Dist: flake8 (>=2.6.0) ; extra == 'dev'
Requires-Dist: ipykernel ; extra == 'dev'
Requires-Dist: pip (>=19.1.1) ; extra == 'dev'
Requires-Dist: pre-commit ; extra == 'dev'
Requires-Dist: pytest ; extra == 'dev'
Requires-Dist: pytest-cov ; extra == 'dev'
Requires-Dist: PyYAML (>=3.11) ; extra == 'dev'
Requires-Dist: setuptools (>=47.0.0) ; extra == 'dev'
Requires-Dist: tox (>=2.3.1) ; extra == 'dev'
Requires-Dist: twine (>=1.11.0) ; extra == 'dev'
Requires-Dist: watchdog (>=0.8.3) ; extra == 'dev'
Requires-Dist: wheel (>=0.31.0) ; extra == 'dev'
Provides-Extra: docs
Requires-Dist: nbsphinx ; extra == 'docs'
Requires-Dist: pandoc ; extra == 'docs'
Requires-Dist: Sphinx (>=1.4.4) ; extra == 'docs'
